apu/__init__.py
apu/__version__.py
apu/git_util.py
apu/trycatch.py
apu/ast/__init__.py
apu/ast/comprehensions.py
apu/ast/keyword_mapping.py
apu/datastructures/__init__.py
apu/datastructures/circularebuffer.py
apu/datastructures/dictionary.py
apu/datastructures/enhanced_list.py
apu/datastructures/memorywrapper.py
apu/dp/__init__.py
apu/dp/blackboard.py
apu/dp/iterator.py
apu/dp/null.py
apu/dp/singleton.py
apu/encoding/__init__.py
apu/encoding/bytes.py
apu/encoding/json/__init__.py
apu/encoding/json/np.py
apu/encoding/msgpack/__init__.py
apu/encoding/msgpack/np.py
apu/exception/__init__.py
apu/exception/dict_key.py
apu/exception/directory.py
apu/exception/io.py
apu/exception/module.py
apu/exception/noteditable.py
apu/exception/readwrongfile.py
apu/exception/unsupporteddatatype.py
apu/geo/Coord.py
apu/geo/__init__.py
apu/io/__init__.py
apu/io/copy.py
apu/io/dill.py
apu/io/file_chunk.py
apu/io/fileformat.py
apu/io/hash.py
apu/io/net.py
apu/io/path.py
apu/io/format/__init__.py
apu/io/format/csv.py
apu/io/format/dill.py
apu/io/format/h5.py
apu/io/format/json.py
apu/io/format/matlab.py
apu/io/format/np.py
apu/io/format/pickel.py
apu/io/format/yaml.py
apu/ml/__init__.py
apu/ml/torch/__init__.py
apu/ml/torch/activations.py
apu/ml/torch/conv.py
apu/ml/torch/util.py
apu/mp/__init__.py
apu/mp/parallel_for.py
apu/mp/thread_funcrun.py
apu/setup/__init__.py
apu/setup/module.py
apu/setup/protobuf.py
apu/setup/version.py
apu/time/__init__.py
apu/time/date_time.py
apu/time/timer.py
apu-0.1.22.0.0.dist-info/LICENSE
apu-0.1.22.0.0.dist-info/METADATA
apu-0.1.22.0.0.dist-info/WHEEL
apu-0.1.22.0.0.dist-info/top_level.txt
apu-0.1.22.0.0.dist-info/RECORD
