Metadata-Version: 2.1
Name: apu
Version: 0.1.22.0.0
Summary: Antons Python Utilities
Home-page: https://github.com/afeldman/apu
Author: Anton Feldmann
Author-email: anton.feldmann@gmail.com
Maintainer: Anton Feldmann
Maintainer-email: anton.feldmann@gmail.com
License: MIT
Download-URL: https://github.com/afeldman/apu
Project-URL: Documentation, https://afeldman.github.io/apu/
Project-URL: Source, https://github.com/afeldman/apu
Project-URL: Tracker, https://github.com/afeldman/apu/issues
Keywords: utility
Platform: Linux
Classifier: Development Status :: 3 - Alpha
Classifier: Environment :: Console
Classifier: Intended Audience :: Developers
Classifier: Intended Audience :: Information Technology
Classifier: License :: OSI Approved :: MIT License
Classifier: Natural Language :: English
Classifier: Operating System :: OS Independent
Classifier: Programming Language :: Python :: 3
Classifier: Programming Language :: Python :: 3 :: Only
Classifier: Programming Language :: Python :: 3.6
Classifier: Programming Language :: Python :: 3.7
Classifier: Programming Language :: Python :: 3.8
Classifier: Topic :: Software Development :: Libraries :: Python Modules
Classifier: Topic :: Software Development
Classifier: Topic :: Utilities
Requires-Python: >=3.7
License-File: LICENSE
Requires-Dist: dill
Requires-Dist: pytz
Requires-Dist: pint
Requires-Dist: tzlocal
Requires-Dist: GitPython
Requires-Dist: numpy
Requires-Dist: mat4py
